README.md
setup.py
apicPython/__init__.py
apicPython/addFabricNode.py
apicPython/addMgmtProvidedOutOfBandContract.py
apicPython/addSecurityDomain.py
apicPython/addUserDomain.py
apicPython/addVmmDomainAssociation.py
apicPython/associateL3OutsideNetworkToBD.py
apicPython/changeCatalogFirmwarePolicy.py
apicPython/changeClusterSize.py
apicPython/chooseRoleForUser.py
apicPython/configureInBandEpgDefault.py
apicPython/configureInterfacePcAndVpc.py
apicPython/connectEpgContract.py
apicPython/createAccessPortPolicyGroup.py
apicPython/createApplication.py
apicPython/createApplicationEpg.py
apicPython/createAttachableAccessEntityprofile.py
apicPython/createBgpRouteReflector.py
apicPython/createBridgeDomain.py
apicPython/createCdpInterfacePolicy.py
apicPython/createContract.py
apicPython/createDhcpRelayLabel.py
apicPython/createDhcpRelayPolicy.py
apicPython/createDnsProfile.py
apicPython/createExternalManagementEntityInstance.py
apicPython/createExternalNetwork.py
apicPython/createFilter.py
apicPython/createFirmwareGroup.py
apicPython/createInterfaceProfile.py
apicPython/createL3EpgProviderOrConsumerContract.py
apicPython/createLacpPolicy.py
apicPython/createLinkLevelPolicy.py
apicPython/createLldpInterfacePolicy.py
apicPython/createLocalUser.py
apicPython/createMaintenanceGroup.py
apicPython/createMo.py
apicPython/createMulticastAddressBlock.py
apicPython/createNodeManagementAddress.py
apicPython/createNodes.py
apicPython/createNodesAndInterfacesProfile.py
apicPython/createOutOfBandContract.py
apicPython/createOutsideFirmwareSource.py
apicPython/createPcInterfacePolicyGroup.py
apicPython/createPhysicalDomain.py
apicPython/createPodPolicyGroup.py
apicPython/createPrivateNetwork.py
apicPython/createRadiusProvider.py
apicPython/createRoutedInterfaceProfile.py
apicPython/createRoutedOutside.py
apicPython/createStaticRoute.py
apicPython/createSubnet.py
apicPython/createTenant.py
apicPython/createVcenterController.py
apicPython/createVcenterCredential.py
apicPython.egg-info/PKG-INFO
apicPython.egg-info/SOURCES.txt
apicPython.egg-info/dependency_links.txt
apicPython.egg-info/top_level.txt