Metadata-Version: 1.0
Name: apicPython
Version: 0.2.7
Summary: This are codes for creating MO in APIC through Python API
Home-page: https://github.com/datacenter/ACI/tree/master/configuration-python
Author: Bon Huang
Author-email: bonhuan@cisco.com
License: Cisco
Keywords: Create MO in Cisco APIC
Platform: UNKNOWN
